setup.py
gaussbi_distributions/Binomialdistribution.py
gaussbi_distributions/Gaussiandistribution.py
gaussbi_distributions/Generaldistribution.py
gaussbi_distributions/__init__.py
gaussbi_distributions.egg-info/PKG-INFO
gaussbi_distributions.egg-info/SOURCES.txt
gaussbi_distributions.egg-info/dependency_links.txt
gaussbi_distributions.egg-info/not-zip-safe
gaussbi_distributions.egg-info/top_level.txt