Metadata-Version: 1.0
Name: gaussbi-distributions
Version: 1.0
Summary: Gaussian and Binomial Distributions
Home-page: UNKNOWN
Author: ['Muhammad Farjad Ali Raza']
Author-email: farjadmohal@gmail.com
License: license.txt
Platform: UNKNOWN
